machinemind_bpe/__init__.py
machinemind_bpe/dependency_check.py
machinemind_bpe/machinemind_bpe.py
machinemind_bpe-1.0.1.dist-info/LICENCE
machinemind_bpe-1.0.1.dist-info/METADATA
machinemind_bpe-1.0.1.dist-info/WHEEL
machinemind_bpe-1.0.1.dist-info/top_level.txt
machinemind_bpe-1.0.1.dist-info/RECORD
