Metadata-Version: 2.1
Name: machinemind-bpe
Version: 1.0.1
Summary: A Byte Pair Encoding (BPE) tokenizer package for CPU and GPU.
Home-page: https://github.com/machineminduzb_v2/bpe_tokenizer
Author: Javokhir
Author-email: machinemind60@gmail.com
License: MIT
Classifier: License :: OSI Approved :: MIT License
Classifier: Programming Language :: Python :: 3
Classifier: Programming Language :: Python :: 3.6
Classifier: Programming Language :: Python :: 3.7
Classifier: Programming Language :: Python :: 3.8
Classifier: Programming Language :: Python :: 3.9
License-File: LICENCE
Requires-Dist: numpy >=1.1.0
Requires-Dist: torch >=1.7.0
Requires-Dist: tqdm >=4.0.0
Requires-Dist: regex >=1.1.1
